flimsay/__init__.py
flimsay/blib.py
flimsay/cli.py
flimsay/constants.py
flimsay/data.py
flimsay/features.py
flimsay/mass.py
flimsay/model.py
flimsay/weights/ccs_model.txt
flimsay/weights/one_over_k0_model.txt
flimsay-0.4.0.dist-info/METADATA
flimsay-0.4.0.dist-info/WHEEL
flimsay-0.4.0.dist-info/entry_points.txt
flimsay-0.4.0.dist-info/top_level.txt
flimsay-0.4.0.dist-info/RECORD
