Metadata-Version: 2.1
Name: flimsay
Version: 0.4.0
Summary: A super simple fast IMS predictor
Author-email: Sebastian Paez <spaez@talus.bio>
License: Apache 2.0
Project-URL: Homepage, https://github.com/TalusBio/flimsay
Project-URL: Documentation, https://TalusBio.github.io/flimsay
Keywords: proteomics,dia,ion mobility
Classifier: Programming Language :: Python :: 3
Classifier: License :: OSI Approved :: Apache Software License
Classifier: Operating System :: OS Independent
Classifier: Topic :: Scientific/Engineering :: Bio-Informatics
Requires-Python: <3.12,>=3.9
Requires-Dist: pandas (>=2.0.0)
Requires-Dist: numpy (==1.24.0)
Requires-Dist: tqdm (>=4.64.1)
Requires-Dist: loguru (>=0.6.0)
Requires-Dist: lightgbm (>=3.3.5)
Requires-Dist: rich-click (>=1.6.1)
Provides-Extra: build
Requires-Dist: nbformat ; extra == 'build'
Requires-Dist: nbclient ; extra == 'build'
Requires-Dist: ipykernel ; extra == 'build'
Requires-Dist: wheel ; extra == 'build'
Requires-Dist: build ; extra == 'build'
Requires-Dist: twine ; extra == 'build'
Provides-Extra: dev
Requires-Dist: ruff (>=0.0.253) ; extra == 'dev'
Requires-Dist: black (>=23.1.0) ; extra == 'dev'
Requires-Dist: isort (>=5.12.0) ; extra == 'dev'
Requires-Dist: pylance (>=0.3.9) ; extra == 'dev'
Requires-Dist: jupyter (>=1.0.0) ; extra == 'dev'
Requires-Dist: pip-tools (>=7.0.0) ; extra == 'dev'
Provides-Extra: plot
Requires-Dist: matplotlib ; extra == 'plot'
Requires-Dist: vizta ; extra == 'plot'
Provides-Extra: test
Requires-Dist: pytest (>=7.2.0) ; extra == 'test'
Requires-Dist: pytest-datadir (>=1.4.1) ; extra == 'test'
Requires-Dist: pytest-cov (>=4.0.0) ; extra == 'test'
